synthesizeme/__init__.py
synthesizeme/__metadata__.py
synthesizeme/personalrm/default_judge.py
synthesizeme/personalrm/personalrm.py
synthesizeme/personalrm/synthesizeme.py
synthesizeme/prompts/llama3b.json
synthesizeme/prompts/llama70b.json
synthesizeme/prompts/llama8b.json
synthesizeme/utils/convert.py
synthesizeme/utils/dspy_methods.py
synthesizeme/utils/format_conv.py
synthesizeme/utils/utils.py
synthesizeme-0.0.1.dist-info/licenses/LICENSE
synthesizeme-0.0.1.dist-info/METADATA
synthesizeme-0.0.1.dist-info/WHEEL
synthesizeme-0.0.1.dist-info/top_level.txt
synthesizeme-0.0.1.dist-info/RECORD
