Metadata-Version: 2.4
Name: SynthesizeMe
Version: 0.0.1
Summary: Learn what Language Models think about you! Synthesize personas from your LLM interactions.
Author-email: Michael Ryan <michaeljryan@stanford.edu>
License: MIT License
Project-URL: homepage, https://github.com/XenonMolecule/SynthesizeMe
Classifier: Development Status :: 3 - Alpha
Classifier: Intended Audience :: Science/Research
Classifier: License :: OSI Approved :: MIT License
Classifier: Operating System :: POSIX :: Linux
Classifier: Programming Language :: Python :: 3
Classifier: Programming Language :: Python :: 3.9
Requires-Python: >=3.9
License-File: LICENSE
Requires-Dist: dspy
Provides-Extra: anthropic
Requires-Dist: anthropic<1.0.0,>=0.18.0; extra == "anthropic"
Dynamic: license-file
